setup.cfg
setup.py
target_gsheet.py
target_gsheet.egg-info/PKG-INFO
target_gsheet.egg-info/SOURCES.txt
target_gsheet.egg-info/dependency_links.txt
target_gsheet.egg-info/entry_points.txt
target_gsheet.egg-info/requires.txt
target_gsheet.egg-info/top_level.txt