Metadata-Version: 1.1
Name: target-gsheet
Version: 0.2.4
Summary: Singer.io target for writing data to Google Sheets
Home-page: https://singer.io
Author: Stitch
Author-email: UNKNOWN
License: UNKNOWN
Platform: UNKNOWN
Classifier: Programming Language :: Python :: 3 :: Only
